uthavu_tools/__init__.py
uthavu_tools/linux-cmds.txt
uthavu_tools/listtools.py
uthavu_tools/vs_hotkey.py
uthavu_tools/vs_hotkey_silence_not_working.py
uthavu_tools/debian_server/__init__.py
uthavu_tools/debian_server/setup_nginx_config.py
uthavu_tools/debian_server/setup_nginx_config_uthavu.py
uthavu_tools/debian_server/setup_nginx_https.py
uthavu_tools/debian_server/usserver.py
uthavu_tools/debian_server/db_backups/adangal_db_backup.py
uthavu_tools/debian_server/db_backups/adangal_remote_backup.py
uthavu_tools/debian_server/db_backups/download_consistent_backup.py
uthavu_tools/debian_server/kleer/__init__.py
uthavu_tools/debian_server/kleer/create_mgmt_role.py
uthavu_tools/debian_server/kleer/create_worker_role.py
uthavu_tools/debian_server/kleer/edit_remote_file.py
uthavu_tools/debian_server/kleer/export_kleer_db.py
uthavu_tools/debian_server/kleer/kleer_front_deploy.py
uthavu_tools/debian_server/kleer/kleer_front_quick_deploy.py
uthavu_tools/debian_server/kleer/local_setup_steps.txt
uthavu_tools/debian_server/kleer/switch_nginx_route.py
uthavu_tools/debian_server/nginx-conf/v2.txt
uthavu_tools/deployment/__init__.py
uthavu_tools/deployment/aud.py
uthavu_tools/git_tools/__init__.py
uthavu_tools/git_tools/auto_checkout_latest_branch.py
uthavu_tools/git_tools/auto_checkout_latest_branch_remote.py
uthavu_tools/git_tools/checkbranch.py
uthavu_tools/git_tools/checkin.py
uthavu_tools/git_tools/cleanbranches.py
uthavu_tools/git_tools/cleanup.py
uthavu_tools/git_tools/createrepo.py
uthavu_tools/git_tools/delete_gitlab_project.py
uthavu_tools/git_tools/just_create_repo.py
uthavu_tools/git_tools/list_repos.py
uthavu_tools/git_tools/list_repos_with_branch.py
uthavu_tools/git_tools/merge_dev_to_main.py
uthavu_tools/git_tools/releasetool.py
uthavu_tools/git_tools/repo_summary.py
uthavu_tools/git_tools/reset_branch.py
uthavu_tools/git_tools/template_files/nextjs/dockerfile
uthavu_tools/git_tools/template_files/php/.gitlab-ci.yml
uthavu_tools-1.0.81.dist-info/licenses/LICENSE
uthavu_tools-1.0.81.dist-info/METADATA
uthavu_tools-1.0.81.dist-info/WHEEL
uthavu_tools-1.0.81.dist-info/entry_points.txt
uthavu_tools-1.0.81.dist-info/top_level.txt
uthavu_tools-1.0.81.dist-info/RECORD
