Metadata-Version: 2.4
Name: uthavu-tools
Version: 1.0.81
Summary: Collection of CLI utilities from Uthavu Software
Author-email: Uthavu Software - The People’s Solution <jawahar.s@uthavu.com>
License: MIT
Requires-Python: >=3.7
License-File: LICENSE
Requires-Dist: GitPython
Dynamic: license-file
